README.txt
setup.py
colradpy/__init__.py
colradpy/adf04_file_paths.py
colradpy/burgess_tully_rates.py
colradpy/colradpy_class.py
colradpy/colradpy_class_BACKUP_6556.py
colradpy/colradpy_class_BASE_6556.py
colradpy/colradpy_class_LOCAL_6556.py
colradpy/colradpy_class_REMOTE_6556.py
colradpy/ecip_rates.py
colradpy/ionization_balance.py
colradpy/ionization_balance_class.py
colradpy/nist_read.py
colradpy/nist_read_txt.py
colradpy/r8necip.py
colradpy/r8yip.py
colradpy/read_adf04_py3_class.py
colradpy/read_adf11.py
colradpy/saha_boltzmann_lte_pops.py
colradpy/solve_matrix_exponential.py
colradpy/split_multiplet.py
colradpy.egg-info/PKG-INFO
colradpy.egg-info/SOURCES.txt
colradpy.egg-info/dependency_links.txt
colradpy.egg-info/requires.txt
colradpy.egg-info/top_level.txt