Metadata-Version: 1.0
Name: colradpy
Version: 1.1
Summary: python collisional radiative solver
Home-page: https://github.com/jladan/package_demo
Author: Curt Johnson
Author-email: caj0026@auburn.edu
License: UNKNOWN
Platform: UNKNOWN
